mosayic/__init__.py
mosayic/auth.py
mosayic/logger.py
mosayic/middleware.py
mosayic/routes.py
mosayic/services/supabase_client.py
mosayic/services/email/__init__.py
mosayic/services/email/email_templates.py
mosayic/services/email/resend_service.py
mosayic/services/notifications/__init__.py
mosayic/services/notifications/fcm.py
mosayic/services/notifications/models.py
mosayic/services/notifications/notification_service.py
mosayic/services/notifications/routes.py
mosayic/webpages/__init__.py
mosayic/webpages/routes.py
mosayic/webpages/templates/data_deletion_request_form.html
mosayic/webpages/templates/data_deletion_request_submitted.html
mosayic/webpages/templates/layout.html
mosayic/webpages/templates/support_page.html
mosayic/webpages/templates/webpage.html
mosayic-0.1.0.dist-info/METADATA
mosayic-0.1.0.dist-info/WHEEL
mosayic-0.1.0.dist-info/RECORD
